{"obj": [{  "paper_accepted": 461,   "num_citations": 0,   "title": "Comparing network protocols via elimination of MAC/PHY effects",   "publication": "IEEE WoWMoM -workshops",   "year": "2010" }, {  "paper_accepted": 461,   "num_citations": 0,   "title": "Towards an energy-efficient attention-aware mobile video player with sensor and face detection support",   "publication": "IEEE WoWMoM -workshops",   "year": "2012" }, {  "paper_accepted": 461,   "num_citations": 0,   "title": "Connectivity analysis of group-based cognitive radio networks",   "publication": "IEEE WoWMoM -workshops",   "year": "2012" }, {  "paper_accepted": 461,   "num_citations": 0,   "title": "Association attacks: Identifying association protocols",   "publication": "IEEE WoWMoM -workshops",   "year": "2012" }, {  "paper_accepted": 461,   "num_citations": 0,   "title": "Diversity decay in opportunistic content sharing systems",   "publication": "IEEE WoWMoM -workshops",   "year": "2011" }, {  "paper_accepted": 461,   "num_citations": 0,   "title": "Channel pool management for video streaming in WLAN",   "publication": "IEEE WoWMoM -workshops",   "year": "2010" }, {  "paper_accepted": 461,   "num_citations": 0,   "title": "Lego-like middleware for heterogeneous sensor and actuator networks",   "publication": "IEEE WoWMoM -workshops",   "year": "2012" }, {  "paper_accepted": 461,   "num_citations": 0,   "title": "Opportunistically supported ubiquitous localization: Machine learning enhancements",   "publication": "IEEE WoWMoM -workshops",   "year": "2010" }, {  "paper_accepted": 461,   "num_citations": 0,   "title": "A secure peer-to-peer web framework",   "publication": "IEEE WoWMoM -workshops",   "year": "2010" }, {  "paper_accepted": 461,   "num_citations": 0,   "title": "Energy-efficient k-class coverage for collaborative classification in Wireless Audio Sensor Networks",   "publication": "IEEE WoWMoM -workshops",   "year": "2011" }, {  "paper_accepted": 461,   "num_citations": 0,   "title": "Efficient broadcast communication in the presence of inside attackers: A non-cooperative game",   "publication": "IEEE WoWMoM -workshops",   "year": "2012" }, {  "paper_accepted": 461,   "num_citations": 0,   "title": "Adaptive data exchange model for opportunistic systems",   "publication": "IEEE WoWMoM -workshops",   "year": "2011" }, {  "paper_accepted": 461,   "num_citations": 0,   "title": "Message from the workshops chairs",   "publication": "IEEE WoWMoM -workshops",   "year": "2011" }, {  "paper_accepted": 461,   "num_citations": 0,   "title": "SVC tunneling for media-aware content delivery: Impact on video quality",   "publication": "IEEE WoWMoM -workshops",   "year": "2011" }, {  "paper_accepted": 461,   "num_citations": 0,   "title": "Power measurement campaign for evaluating the energy efficiency of current NICs",   "publication": "IEEE WoWMoM -workshops",   "year": "2011" }, {  "paper_accepted": 461,   "num_citations": 0,   "title": "Addressing non-homogeneities in a ubiquitous P2P platform for context exchange",   "publication": "IEEE WoWMoM -workshops",   "year": "2012" }, {  "paper_accepted": 461,   "num_citations": 0,   "title": "User satisfaction-based resource allocation for GEO satellites",   "publication": "IEEE WoWMoM -workshops",   "year": "2012" }, {  "paper_accepted": 461,   "num_citations": 0,   "title": "Welcome message from the VTP 2012 Chairs",   "publication": "IEEE WoWMoM -workshops",   "year": "2012" }, {  "paper_accepted": 461,   "num_citations": 1,   "title": "Performance study of the Better Approach to Mobile Adhoc Networking (BATMAN) protocol in the context of asymmetric links",   "publication": "IEEE WoWMoM -workshops",   "year": "2012" }, {  "paper_accepted": 461,   "num_citations": 0,   "title": "Remote configuration and deployment of sensor drivers for a medical bluetooth sensor gateway",   "publication": "IEEE WoWMoM -workshops",   "year": "2011" }]}
