{"obj": [{  "paper_accepted": 207,   "num_citations": 20,   "title": "Addressing the P2P bootstrap problem for small overlay networks",   "publication": "IEEE Conference on Peer-to-Peer Computing",   "year": "2010" }, {  "paper_accepted": 207,   "num_citations": 21,   "title": "Autonomous nat traversal",   "publication": "IEEE Conference on Peer-to-Peer Computing",   "year": "2010" }, {  "paper_accepted": 207,   "num_citations": 20,   "title": "A measurement study of the Wuala on-line storage service",   "publication": "IEEE Conference on Peer-to-Peer Computing",   "year": "2012" }, {  "paper_accepted": 207,   "num_citations": 18,   "title": "Improving accuracy and coverage in an internet-deployed reputation mechanism",   "publication": "IEEE Conference on Peer-to-Peer Computing",   "year": "2010" }, {  "paper_accepted": 207,   "num_citations": 5,   "title": "MONAC: SNS message dissemination over smartphone-based DTN and cloud",   "publication": "IEEE Conference on Peer-to-Peer Computing",   "year": "2011" }, {  "paper_accepted": 207,   "num_citations": 5,   "title": "B-Tracker: improving load balancing and efficiency in distributed P2P trackers",   "publication": "IEEE Conference on Peer-to-Peer Computing",   "year": "2011" }, {  "paper_accepted": 207,   "num_citations": 5,   "title": "SocialHelpers: Introducing social trust to ameliorate churn in P2P reputation systems",   "publication": "IEEE Conference on Peer-to-Peer Computing",   "year": "2011" }, {  "paper_accepted": 207,   "num_citations": 5,   "title": "Adaptive load balancing in KAD",   "publication": "IEEE Conference on Peer-to-Peer Computing",   "year": "2011" }, {  "paper_accepted": 207,   "num_citations": 25,   "title": "CliqueStream: an efficient and fault-resilient live streaming network on a clustered peer-to-peer overlay",   "publication": "IEEE Conference on Peer-to-Peer Computing",   "year": "2008" }, {  "paper_accepted": 207,   "num_citations": 17,   "title": "CloudShield: Efficient anti-malware smartphone patching with a P2P network on the cloud",   "publication": "IEEE Conference on Peer-to-Peer Computing",   "year": "2012" }, {  "paper_accepted": 207,   "num_citations": 18,   "title": "Boosting gossip for live streaming",   "publication": "IEEE Conference on Peer-to-Peer Computing",   "year": "2010" }, {  "paper_accepted": 207,   "num_citations": 24,   "title": "Chordella-a hierarchical peer-to-peer overlay implementation for heterogeneous, mobile environments",   "publication": "IEEE Conference on Peer-to-Peer Computing",   "year": "2008" }, {  "paper_accepted": 207,   "num_citations": 25,   "title": "The impact of NAT on BitTorrent-like P2P systems",   "publication": "IEEE Conference on Peer-to-Peer Computing",   "year": "2009" }, {  "paper_accepted": 207,   "num_citations": 22,   "title": "A flexible divide-and-conquer protocol for multi-view peer-to-peer live streaming",   "publication": "IEEE Conference on Peer-to-Peer Computing",   "year": "2009" }, {  "paper_accepted": 207,   "num_citations": 22,   "title": "An efficient distributed PKI for structured P2P networks",   "publication": "IEEE Conference on Peer-to-Peer Computing",   "year": "2009" }, {  "paper_accepted": 207,   "num_citations": 21,   "title": "Analysis of failure correlation impact on peer-to-peer storage systems",   "publication": "IEEE Conference on Peer-to-Peer Computing",   "year": "2009" }, {  "paper_accepted": 207,   "num_citations": 21,   "title": "Monitoring and management of structured peer-to-peer systems",   "publication": "IEEE Conference on Peer-to-Peer Computing",   "year": "2009" }, {  "paper_accepted": 207,   "num_citations": 23,   "title": "Embracing the peer next door: Proximity in kademlia",   "publication": "IEEE Conference on Peer-to-Peer Computing",   "year": "2008" }, {  "paper_accepted": 207,   "num_citations": 24,   "title": "IgorFs: A distributed P2P file system",   "publication": "IEEE Conference on Peer-to-Peer Computing",   "year": "2008" }, {  "paper_accepted": 207,   "num_citations": 5,   "title": "Inferring peer centrality in socially-informed peer-to-peer systems",   "publication": "IEEE Conference on Peer-to-Peer Computing",   "year": "2011" }]}
