{"obj": [{  "paper_accepted": 594,   "num_citations": 7,   "title": "Powering down for energy efficient peer-to-peer file distribution",   "publication": "Sigmetrics",   "year": "2011" }, {  "paper_accepted": 594,   "num_citations": 7,   "title": "Fair sampling across network flow measurements",   "publication": "Sigmetrics",   "year": "2012" }, {  "paper_accepted": 594,   "num_citations": 7,   "title": "Towards multihop available bandwidth estimation",   "publication": "Sigmetrics",   "year": "2009" }, {  "paper_accepted": 594,   "num_citations": 7,   "title": "Towards architecture independent metrics for multicore performance analysis",   "publication": "Sigmetrics",   "year": "2011" }, {  "paper_accepted": 594,   "num_citations": 7,   "title": "Rigorous statistical analysis of internet loss measurements",   "publication": "Sigmetrics",   "year": "2010" }, {  "paper_accepted": 594,   "num_citations": 8,   "title": "On the efficiency of perfect simulation in monotone queueing networks",   "publication": "Sigmetrics",   "year": "2011" }, {  "paper_accepted": 594,   "num_citations": 8,   "title": "Characterizing continuous time random walks on time varying graphs",   "publication": "Sigmetrics",   "year": "2012" }, {  "paper_accepted": 594,   "num_citations": 7,   "title": "An empirical study of flooding in mesh networks",   "publication": "Sigmetrics",   "year": "2009" }, {  "paper_accepted": 594,   "num_citations": 7,   "title": "A novel DTN based energy neutral transfer scheme for energy harvested WSN Gateways",   "publication": "Sigmetrics",   "year": "2011" }, {  "paper_accepted": 594,   "num_citations": 8,   "title": "Evaluating the performance of single and multiple core processors with PCMARK\u00ae 05 and benchmark analysis",   "publication": "Sigmetrics",   "year": "2008" }, {  "paper_accepted": 594,   "num_citations": 8,   "title": "An overview of OpenAirInterface wireless network emulation methodology",   "publication": "Sigmetrics",   "year": "2008" }, {  "paper_accepted": 594,   "num_citations": 7,   "title": "Fluid computation of the performance: energy tradeoff in large scale Markov models",   "publication": "Sigmetrics",   "year": "2011" }, {  "paper_accepted": 594,   "num_citations": 7,   "title": "Model-driven optimization of opportunistic routing",   "publication": "Sigmetrics",   "year": "2011" }, {  "paper_accepted": 594,   "num_citations": 7,   "title": "Durability of replicated distributed storage systems",   "publication": "Sigmetrics",   "year": "2008" }, {  "paper_accepted": 594,   "num_citations": 7,   "title": "Product environmental metrics for printers",   "publication": "Sigmetrics",   "year": "2010" }, {  "paper_accepted": 594,   "num_citations": 6,   "title": "Admission control policies for a multi-class QoS-aware service oriented architecture",   "publication": "Sigmetrics",   "year": "2012" }, {  "paper_accepted": 594,   "num_citations": 6,   "title": "Modeling randomness in network traffic",   "publication": "Sigmetrics",   "year": "2012" }, {  "paper_accepted": 594,   "num_citations": 6,   "title": "Guaranteeing user welfare in network service: comparison of two subsidy schemes",   "publication": "Sigmetrics",   "year": "2012" }, {  "paper_accepted": 594,   "num_citations": 6,   "title": "ADP: automated diagnosis of performance pathologies using hardware events",   "publication": "Sigmetrics",   "year": "2012" }, {  "paper_accepted": 594,   "num_citations": 6,   "title": "How well can congestion pricing neutralize denial of service attacks?",   "publication": "Sigmetrics",   "year": "2012" }]}
