{"obj": [{  "paper_accepted": 566,   "num_citations": 47,   "title": "XL: An efficient network routing algorithm",   "publication": "Sigcomm -measurement -networked -workshop",   "year": "2008" }, {  "paper_accepted": 566,   "num_citations": 51,   "title": "Tool release: gathering 802.11 n traces with channel state information",   "publication": "Sigcomm -measurement -networked -workshop",   "year": "2011" }, {  "paper_accepted": 566,   "num_citations": 45,   "title": "Shedding light on the glue logic of the internet routing architecture",   "publication": "Sigcomm -measurement -networked -workshop",   "year": "2008" }, {  "paper_accepted": 566,   "num_citations": 47,   "title": "Fighting online click-fraud using bluff ads",   "publication": "Sigcomm -measurement -networked -workshop",   "year": "2010" }, {  "paper_accepted": 566,   "num_citations": 52,   "title": "The power of prediction: Cloud bandwidth and cost reduction",   "publication": "Sigcomm -measurement -networked -workshop",   "year": "2011" }, {  "paper_accepted": 566,   "num_citations": 0,   "title": "Report on the SIGCOMM 2011 Conference",   "publication": "Sigcomm -measurement -networked -workshop",   "year": "2012" }, {  "paper_accepted": 566,   "num_citations": 0,   "title": "A Secure Model for Cloud Computing Based Storage and Retrieval",   "publication": "Sigcomm -measurement -networked -workshop",   "year": "2009" }, {  "paper_accepted": 566,   "num_citations": 0,   "title": "Unified Network Information Services (UNIS) allow users to discover network services and capabilities",   "publication": "Sigcomm -measurement -networked -workshop",   "year": null }, {  "paper_accepted": 566,   "num_citations": 47,   "title": "Generic and automatic address configuration for data center networks",   "publication": "Sigcomm -measurement -networked -workshop",   "year": "2011" }, {  "paper_accepted": 566,   "num_citations": 46,   "title": "Architecting for innovation",   "publication": "Sigcomm -measurement -networked -workshop",   "year": "2011" }, {  "paper_accepted": 566,   "num_citations": 44,   "title": "SoftCast: one-size-fits-all wireless video",   "publication": "Sigcomm -measurement -networked -workshop",   "year": "2011" }, {  "paper_accepted": 566,   "num_citations": 42,   "title": "What would Darwin think about clean-slate architectures?",   "publication": "Sigcomm -measurement -networked -workshop",   "year": "2008" }, {  "paper_accepted": 566,   "num_citations": 43,   "title": "Probabilistic lossy counting: an efficient algorithm for finding heavy hitters",   "publication": "Sigcomm -measurement -networked -workshop",   "year": "2008" }, {  "paper_accepted": 566,   "num_citations": 45,   "title": "On the stability of the information carried by traffic flow features at the packet level",   "publication": "Sigcomm -measurement -networked -workshop",   "year": "2009" }, {  "paper_accepted": 566,   "num_citations": 44,   "title": "Insomnia in the access: or how to curb access network related energy consumption",   "publication": "Sigcomm -measurement -networked -workshop",   "year": "2011" }, {  "paper_accepted": 566,   "num_citations": 41,   "title": "iNFAnt: NFA pattern matching on GPGPU devices",   "publication": "Sigcomm -measurement -networked -workshop",   "year": "2010" }, {  "paper_accepted": 566,   "num_citations": 40,   "title": "PLUG: flexible lookup modules for rapid deployment of new protocols in high-speed routers",   "publication": "Sigcomm -measurement -networked -workshop",   "year": "2009" }, {  "paper_accepted": 566,   "num_citations": 40,   "title": "Cyclops: the AS-level connectivity observatory",   "publication": "Sigcomm -measurement -networked -workshop",   "year": "2008" }, {  "paper_accepted": 566,   "num_citations": 42,   "title": "A Day at the Root of the Internet",   "publication": "Sigcomm -measurement -networked -workshop",   "year": "2008" }, {  "paper_accepted": 566,   "num_citations": 38,   "title": "Detecting the performance impact of upgrades in large operational networks",   "publication": "Sigcomm -measurement -networked -workshop",   "year": "2011" }]}
