{"obj": [{  "paper_accepted": 198,   "num_citations": 10,   "title": "Bluemonarch: a system for evaluating bluetooth applications in the wild",   "publication": "ACM Conference on Mobile Systems, Applications, and Services",   "year": "2009" }, {  "paper_accepted": 198,   "num_citations": 9,   "title": "Characterizing the transport behaviour of the short message service",   "publication": "ACM Conference on Mobile Systems, Applications, and Services",   "year": "2010" }, {  "paper_accepted": 198,   "num_citations": 10,   "title": "Fidelity-aware replication for mobile devices",   "publication": "ACM Conference on Mobile Systems, Applications, and Services",   "year": "2009" }, {  "paper_accepted": 198,   "num_citations": 9,   "title": "Demo: SignalGuru: leveraging mobile phones for collaborative traffic signal schedule advisory",   "publication": "ACM Conference on Mobile Systems, Applications, and Services",   "year": "2011" }, {  "paper_accepted": 198,   "num_citations": 10,   "title": "ExerLink: enabling pervasive social exergames with heterogeneous exercise devices",   "publication": "ACM Conference on Mobile Systems, Applications, and Services",   "year": "2012" }, {  "paper_accepted": 198,   "num_citations": 8,   "title": "CiAO/IP: a highly configurable aspect-oriented IP stack",   "publication": "ACM Conference on Mobile Systems, Applications, and Services",   "year": "2012" }, {  "paper_accepted": 198,   "num_citations": 8,   "title": "Isolating and analyzing fraud activities in a large cellular network via voice call graph analysis",   "publication": "ACM Conference on Mobile Systems, Applications, and Services",   "year": "2012" }, {  "paper_accepted": 198,   "num_citations": 8,   "title": "Demo: prototyping UWB-enabled enhants",   "publication": "ACM Conference on Mobile Systems, Applications, and Services",   "year": "2011" }, {  "paper_accepted": 198,   "num_citations": 7,   "title": "Demo: Quality-adaptive video streaming with dynamic bandwidth aggregation on roaming, multi-homed clients",   "publication": "ACM Conference on Mobile Systems, Applications, and Services",   "year": "2011" }, {  "paper_accepted": 198,   "num_citations": 6,   "title": "Demo: bankrupting the jammer",   "publication": "ACM Conference on Mobile Systems, Applications, and Services",   "year": "2011" }, {  "paper_accepted": 198,   "num_citations": 7,   "title": "Opaak: using mobile phones to limit anonymous identities online",   "publication": "ACM Conference on Mobile Systems, Applications, and Services",   "year": "2012" }, {  "paper_accepted": 198,   "num_citations": 6,   "title": "Poster: gait-based smartphone user identification",   "publication": "ACM Conference on Mobile Systems, Applications, and Services",   "year": "2011" }, {  "paper_accepted": 198,   "num_citations": 7,   "title": "Opportunistic alignment of advertisement delivery with cellular basestation overloads",   "publication": "ACM Conference on Mobile Systems, Applications, and Services",   "year": "2011" }, {  "paper_accepted": 198,   "num_citations": 6,   "title": "Demo: using mobile devices to personalize pervasive displays",   "publication": "ACM Conference on Mobile Systems, Applications, and Services",   "year": "2012" }, {  "paper_accepted": 198,   "num_citations": 6,   "title": "Demo: visual mimo based LED-camera communication applied to automobile safety",   "publication": "ACM Conference on Mobile Systems, Applications, and Services",   "year": "2011" }, {  "paper_accepted": 198,   "num_citations": 5,   "title": "Poster: a context-aware framework for mobile applications",   "publication": "ACM Conference on Mobile Systems, Applications, and Services",   "year": "2011" }, {  "paper_accepted": 198,   "num_citations": 5,   "title": "Performance study of active tracking in a cellular network using a modular signaling platform",   "publication": "ACM Conference on Mobile Systems, Applications, and Services",   "year": "2010" }, {  "paper_accepted": 198,   "num_citations": 4,   "title": "Precise indoor localization using PHY information",   "publication": "ACM Conference on Mobile Systems, Applications, and Services",   "year": "2011" }, {  "paper_accepted": 198,   "num_citations": 4,   "title": "Poster: a green solution for intelligent metropolitan heating system with uSDcard",   "publication": "ACM Conference on Mobile Systems, Applications, and Services",   "year": "2011" }, {  "paper_accepted": 198,   "num_citations": 3,   "title": "Poster: a hybrid approach for indoor mobile phone localization",   "publication": "ACM Conference on Mobile Systems, Applications, and Services",   "year": "2012" }]}
