{"obj": [{  "paper_accepted": 839,   "num_citations": 9,   "title": "Integrating the IAC neural network in ontology mapping",   "publication": "\Conference on World Wide Web\",   "year": "2008" }, {  "paper_accepted": 839,   "num_citations": 9,   "title": "Buzz-based recommender system",   "publication": "\Conference on World Wide Web\",   "year": "2009" }, {  "paper_accepted": 839,   "num_citations": 9,   "title": "Extracting client-side web application code",   "publication": "\Conference on World Wide Web\",   "year": "2012" }, {  "paper_accepted": 839,   "num_citations": 9,   "title": "A large-scale active learning system for topical categorization on the web",   "publication": "\Conference on World Wide Web\",   "year": "2010" }, {  "paper_accepted": 839,   "num_citations": 9,   "title": "Ajax for mobility: mobileweaver ajax framework",   "publication": "\Conference on World Wide Web\",   "year": "2008" }, {  "paper_accepted": 839,   "num_citations": 10,   "title": "A case for query by image and text content: searching computer help using screenshots and keywords",   "publication": "\Conference on World Wide Web\",   "year": "2011" }, {  "paper_accepted": 839,   "num_citations": 9,   "title": "Towards robust service compositions in the context of functionally diverse services",   "publication": "\Conference on World Wide Web\",   "year": "2012" }, {  "paper_accepted": 839,   "num_citations": 9,   "title": "Enterprise and desktop search",   "publication": "\Conference on World Wide Web\",   "year": "2010" }, {  "paper_accepted": 839,   "num_citations": 9,   "title": "Behavioral classification on the click graph",   "publication": "\Conference on World Wide Web\",   "year": "2008" }, {  "paper_accepted": 839,   "num_citations": 9,   "title": "Mining cultural differences from a large number of geotagged photos",   "publication": "\Conference on World Wide Web\",   "year": "2009" }, {  "paper_accepted": 839,   "num_citations": 10,   "title": "Modeling semantics and structure of discussion threads",   "publication": "\Conference on World Wide Web\",   "year": "2009" }, {  "paper_accepted": 839,   "num_citations": 9,   "title": "A P2P based distributed services network for next generation mobile internet communications",   "publication": "\Conference on World Wide Web\",   "year": "2009" }, {  "paper_accepted": 839,   "num_citations": 9,   "title": "Personalized multimedia web summarizer for tourist",   "publication": "\Conference on World Wide Web\",   "year": "2008" }, {  "paper_accepted": 839,   "num_citations": 9,   "title": "Conversion rate based bid adjustment for sponsored search",   "publication": "\Conference on World Wide Web\",   "year": "2010" }, {  "paper_accepted": 839,   "num_citations": 9,   "title": "Partitioned multi-indexing: bringing order to social search",   "publication": "\Conference on World Wide Web\",   "year": "2012" }, {  "paper_accepted": 839,   "num_citations": 10,   "title": "Cascading style sheets: a novel approach towards productive styling with today&#39;s standards",   "publication": "\Conference on World Wide Web\",   "year": "2009" }, {  "paper_accepted": 839,   "num_citations": 9,   "title": "Analyzing seller practices in a Brazilian marketplace",   "publication": "\Conference on World Wide Web\",   "year": "2009" }, {  "paper_accepted": 839,   "num_citations": 10,   "title": "DOHA: scalable real-time web applications through adaptive concurrent execution",   "publication": "\Conference on World Wide Web\",   "year": "2012" }, {  "paper_accepted": 839,   "num_citations": 9,   "title": "SAFE extensibility of data-driven web applications",   "publication": "\Conference on World Wide Web\",   "year": "2012" }, {  "paper_accepted": 839,   "num_citations": 10,   "title": "iRIN: image retrieval in image-rich information networks",   "publication": "\Conference on World Wide Web\",   "year": "2010" }]}
