{"obj": [{  "paper_accepted": 556,   "num_citations": 1,   "title": "Threshold-Based Rate Control for Multimedia Transport over Markovian Wireless Channels",   "publication": "IEEE Wireless Communications and Networking Conference WCNC",   "year": "2008" }, {  "paper_accepted": 556,   "num_citations": 1,   "title": "Dynamic Base Station Relocation in Cognitive Mesh Networks Using Packet Switch",   "publication": "IEEE Wireless Communications and Networking Conference WCNC",   "year": "2008" }, {  "paper_accepted": 556,   "num_citations": 4,   "title": "Area concentric beacons localization for wireless sensor networks",   "publication": "IEEE Wireless Communications and Networking Conference WCNC",   "year": "2008" }, {  "paper_accepted": 556,   "num_citations": 1,   "title": "On throughput limit of multi-rate IEEE 802.11 WLANs: Basic access vs. RTS/CTS access",   "publication": "IEEE Wireless Communications and Networking Conference WCNC",   "year": "2008" }, {  "paper_accepted": 556,   "num_citations": 1,   "title": "Cross-Layer Issues for Cooperative Networks",   "publication": "IEEE Wireless Communications and Networking Conference WCNC",   "year": "2008" }, {  "paper_accepted": 556,   "num_citations": 1,   "title": "Optimizing fast handover for mobile IPv6 with dynamic price",   "publication": "IEEE Wireless Communications and Networking Conference WCNC",   "year": "2008" }, {  "paper_accepted": 556,   "num_citations": 1,   "title": "An Intelligent Tunneling Framework for Always Best Connected Support in Network Mobility (NEMO)",   "publication": "IEEE Wireless Communications and Networking Conference WCNC",   "year": "2008" }, {  "paper_accepted": 556,   "num_citations": 1,   "title": "Iterative decoding of serial concatenated differential space-time block coding under unknown fading channels",   "publication": "IEEE Wireless Communications and Networking Conference WCNC",   "year": "2008" }, {  "paper_accepted": 556,   "num_citations": 1,   "title": "Asymptotic Outage Analysis of Large Size Correlated MIMO Systems",   "publication": "IEEE Wireless Communications and Networking Conference WCNC",   "year": "2008" }, {  "paper_accepted": 556,   "num_citations": 1,   "title": "Approximate maximum likelihood detectors for MIMO spatial multiplexing systems",   "publication": "IEEE Wireless Communications and Networking Conference WCNC",   "year": "2008" }, {  "paper_accepted": 556,   "num_citations": 1,   "title": "Analysis of low latency mac protocols for clustered sensor networks",   "publication": "IEEE Wireless Communications and Networking Conference WCNC",   "year": "2008" }, {  "paper_accepted": 556,   "num_citations": 2,   "title": "Detection strategies for ds-ss systems employing parity bit selected spreading",   "publication": "IEEE Wireless Communications and Networking Conference WCNC",   "year": "2008" }, {  "paper_accepted": 556,   "num_citations": 1,   "title": "Space-Time Codes Versus Random Beamforming in Cooperative Multi-Hop Wireless Networks",   "publication": "IEEE Wireless Communications and Networking Conference WCNC",   "year": "2008" }, {  "paper_accepted": 556,   "num_citations": 1,   "title": "QoS for Ad Hoc Networks Using an Empirical Model",   "publication": "IEEE Wireless Communications and Networking Conference WCNC",   "year": "2008" }, {  "paper_accepted": 556,   "num_citations": 1,   "title": "Exact performance analysis of joint adaptive modulation and power loading transmission in multi-channel system",   "publication": "IEEE Wireless Communications and Networking Conference WCNC",   "year": "2008" }, {  "paper_accepted": 556,   "num_citations": 1,   "title": "A suboptimal lq power control algorithm for a cdma wireless system",   "publication": "IEEE Wireless Communications and Networking Conference WCNC",   "year": "2008" }, {  "paper_accepted": 556,   "num_citations": 1,   "title": "Decoding on graphs: LDPC-Coded MISO systems and belief propagation",   "publication": "IEEE Wireless Communications and Networking Conference WCNC",   "year": "2008" }, {  "paper_accepted": 556,   "num_citations": 1,   "title": "On the feedback channel for MIMO beamforming",   "publication": "IEEE Wireless Communications and Networking Conference WCNC",   "year": "2008" }, {  "paper_accepted": 556,   "num_citations": 1,   "title": "Exact BER performance of asynchronous MC-DS-CDMA over Nakagami-m fading channels",   "publication": "IEEE Wireless Communications and Networking Conference WCNC",   "year": "2008" }, {  "paper_accepted": 556,   "num_citations": 1,   "title": "A Detection Algorithm for MIMO Transmission Using Poly-Diagonalization and Trellis Decoding",   "publication": "IEEE Wireless Communications and Networking Conference WCNC",   "year": "2008" }]}
