{"obj": [{  "paper_accepted": 1030,   "num_citations": 3,   "title": "Network-leading association scheme in ieee 802.11 wireless mesh networks",   "publication": "IEEE International Conference on Communications ICC -Workshops",   "year": "2011" }, {  "paper_accepted": 1030,   "num_citations": 3,   "title": "Design of p-cycles under a wavelength continuity assumption",   "publication": "IEEE International Conference on Communications ICC -Workshops",   "year": "2011" }, {  "paper_accepted": 1030,   "num_citations": 3,   "title": "Optimal Power Allocation over a Fading MAC with Varying Observation SNRS in Resource Constrained Wireless Sensor Network",   "publication": "IEEE International Conference on Communications ICC -Workshops",   "year": "2011" }, {  "paper_accepted": 1030,   "num_citations": 3,   "title": "Joint linear mmse processing for two-way non-regenerative MIMO relay systems",   "publication": "IEEE International Conference on Communications ICC -Workshops",   "year": "2011" }, {  "paper_accepted": 1030,   "num_citations": 3,   "title": "A robust collaborative filtering algorithm using ordered logistic regression",   "publication": "IEEE International Conference on Communications ICC -Workshops",   "year": "2011" }, {  "paper_accepted": 1030,   "num_citations": 3,   "title": "How contact probing affects the transmission capacity and energy consumption in DTNs",   "publication": "IEEE International Conference on Communications ICC -Workshops",   "year": "2011" }, {  "paper_accepted": 1030,   "num_citations": 3,   "title": "Comparison of the Detrimental Effects of Trapping Sets in LDPC Codes",   "publication": "IEEE International Conference on Communications ICC -Workshops",   "year": "2011" }, {  "paper_accepted": 1030,   "num_citations": 3,   "title": "Measurement aided model design for WCDMA link error statistics",   "publication": "IEEE International Conference on Communications ICC -Workshops",   "year": "2011" }, {  "paper_accepted": 1030,   "num_citations": 3,   "title": "DFA-based regular expression matching on compressed traffic",   "publication": "IEEE International Conference on Communications ICC -Workshops",   "year": "2011" }, {  "paper_accepted": 1030,   "num_citations": 3,   "title": "Per-subcarrier antenna selection for OFDMA-based cognitive radio systems",   "publication": "IEEE International Conference on Communications ICC -Workshops",   "year": "2011" }, {  "paper_accepted": 1030,   "num_citations": 3,   "title": "Minimizing retrieval cost of multi-layer content distribution systems",   "publication": "IEEE International Conference on Communications ICC -Workshops",   "year": "2011" }, {  "paper_accepted": 1030,   "num_citations": 3,   "title": "Max-flow protection using network coding",   "publication": "IEEE International Conference on Communications ICC -Workshops",   "year": "2011" }, {  "paper_accepted": 1030,   "num_citations": 3,   "title": "SAMA: Serverless Anonymous Mutual Authentication for Low-Cost RFID Tags",   "publication": "IEEE International Conference on Communications ICC -Workshops",   "year": "2011" }, {  "paper_accepted": 1030,   "num_citations": 3,   "title": "Dispersing hotspot traffic in backup topology for IP fast reroute",   "publication": "IEEE International Conference on Communications ICC -Workshops",   "year": "2011" }, {  "paper_accepted": 1030,   "num_citations": 3,   "title": "Hybrid in-network query processing framework for wireless sensor networks",   "publication": "IEEE International Conference on Communications ICC -Workshops",   "year": "2011" }, {  "paper_accepted": 1030,   "num_citations": 3,   "title": "MIMO inter-cell interference management through base station cooperation",   "publication": "IEEE International Conference on Communications ICC -Workshops",   "year": "2011" }, {  "paper_accepted": 1030,   "num_citations": 3,   "title": "An energy efficient prediction-based technique for tracking moving objects in WSNs",   "publication": "IEEE International Conference on Communications ICC -Workshops",   "year": "2011" }, {  "paper_accepted": 1030,   "num_citations": 3,   "title": "Performance analysis of a multi-hop communication system with decode-and-forward relaying",   "publication": "IEEE International Conference on Communications ICC -Workshops",   "year": "2011" }, {  "paper_accepted": 1030,   "num_citations": 3,   "title": "K-User MIMO X network system with perfect interference alignment",   "publication": "IEEE International Conference on Communications ICC -Workshops",   "year": "2011" }, {  "paper_accepted": 1030,   "num_citations": 3,   "title": "On the effective capacity of two-hop communication systems",   "publication": "IEEE International Conference on Communications ICC -Workshops",   "year": "2011" }]}
