{"obj": [{  "paper_accepted": 160,   "num_citations": 3,   "title": "Collecting router information for error diagnosis and troubleshooting in home networks",   "publication": "IEEE Conference on Local Computer Networks (LCN)",   "year": "2011" }, {  "paper_accepted": 160,   "num_citations": 4,   "title": "Tracking targets in quantized areas with wireless sensor networks",   "publication": "IEEE Conference on Local Computer Networks (LCN)",   "year": "2011" }, {  "paper_accepted": 160,   "num_citations": 3,   "title": "dVirt: A virtualized infrastructure for experimenting BGP routing",   "publication": "IEEE Conference on Local Computer Networks (LCN)",   "year": "2011" }, {  "paper_accepted": 160,   "num_citations": 3,   "title": "Implementation of WFQ in a distributed open software router",   "publication": "IEEE Conference on Local Computer Networks (LCN)",   "year": "2011" }, {  "paper_accepted": 160,   "num_citations": 3,   "title": "Mobile VoIP user experience in LTE",   "publication": "IEEE Conference on Local Computer Networks (LCN)",   "year": "2011" }, {  "paper_accepted": 160,   "num_citations": 3,   "title": "Planet YouTube: Global, measurement-based performance analysis of viewer;&#39;s experience watching user generated videos",   "publication": "IEEE Conference on Local Computer Networks (LCN)",   "year": "2011" }, {  "paper_accepted": 160,   "num_citations": 3,   "title": "SDF\u2014Solar-aware distributed flow in wireless sensor networks",   "publication": "IEEE Conference on Local Computer Networks (LCN)",   "year": "2011" }, {  "paper_accepted": 160,   "num_citations": 3,   "title": "Wireless technology agnostic real-time localization in urban areas",   "publication": "IEEE Conference on Local Computer Networks (LCN)",   "year": "2011" }, {  "paper_accepted": 160,   "num_citations": 3,   "title": "Effective utilization of place as a resource in pocket switched networks",   "publication": "IEEE Conference on Local Computer Networks (LCN)",   "year": "2011" }, {  "paper_accepted": 160,   "num_citations": 3,   "title": "Intrusion detection system using optimum-path forest",   "publication": "IEEE Conference on Local Computer Networks (LCN)",   "year": "2011" }, {  "paper_accepted": 160,   "num_citations": 3,   "title": "Toward a high-fidelity wireless sensor network for rehabilitation supervision",   "publication": "IEEE Conference on Local Computer Networks (LCN)",   "year": "2011" }, {  "paper_accepted": 160,   "num_citations": 3,   "title": "DuDE: A distributed computing system using a decentralized P2P environment",   "publication": "IEEE Conference on Local Computer Networks (LCN)",   "year": "2011" }, {  "paper_accepted": 160,   "num_citations": 3,   "title": "Scalability issues in localizing Things",   "publication": "IEEE Conference on Local Computer Networks (LCN)",   "year": "2011" }, {  "paper_accepted": 160,   "num_citations": 3,   "title": "AWARE: Activity aware network clustering for wireless sensor networks",   "publication": "IEEE Conference on Local Computer Networks (LCN)",   "year": "2011" }, {  "paper_accepted": 160,   "num_citations": 2,   "title": "A power-aware framework for distributed data fusion application in wireless sensor networks",   "publication": "IEEE Conference on Local Computer Networks (LCN)",   "year": "2011" }, {  "paper_accepted": 160,   "num_citations": 2,   "title": "Mercury-like routing for high mobility wireless ad hoc networks",   "publication": "IEEE Conference on Local Computer Networks (LCN)",   "year": "2011" }, {  "paper_accepted": 160,   "num_citations": 2,   "title": "Using sensor technology to protect an endangered species: A case study",   "publication": "IEEE Conference on Local Computer Networks (LCN)",   "year": "2011" }, {  "paper_accepted": 160,   "num_citations": 2,   "title": "Optimal throughput for 802.11 DCF with multiple packet reception",   "publication": "IEEE Conference on Local Computer Networks (LCN)",   "year": "2011" }, {  "paper_accepted": 160,   "num_citations": 2,   "title": "Flock detection based duty cycle scheduling in mobile wireless sensor networks",   "publication": "IEEE Conference on Local Computer Networks (LCN)",   "year": "2011" }, {  "paper_accepted": 160,   "num_citations": 2,   "title": "Analysis of quantization effects on performance of hierarchical cooperation schemes in Ad-hoc wireless networks",   "publication": "IEEE Conference on Local Computer Networks (LCN)",   "year": "2011" }]}
