{"obj": [{  "paper_accepted": 1130,   "num_citations": 6,   "title": "Adjacent Channel Interference Cancelation in Fractional Sampling OFDM Receiver",   "publication": "Vehicular Technology Conference VTC -workshops",   "year": "2011" }, {  "paper_accepted": 1130,   "num_citations": 6,   "title": "Why VANET beaconing is more than simple broadcast",   "publication": "Vehicular Technology Conference VTC -workshops",   "year": "2011" }, {  "paper_accepted": 1130,   "num_citations": 6,   "title": "Best sensor selection for an iterative REM construction",   "publication": "Vehicular Technology Conference VTC -workshops",   "year": "2011" }, {  "paper_accepted": 1130,   "num_citations": 6,   "title": "Rate and outage performance of non-regenerative two-way relaying protocols with direct link",   "publication": "Vehicular Technology Conference VTC -workshops",   "year": "2011" }, {  "paper_accepted": 1130,   "num_citations": 6,   "title": "Bayesian channel estimation techniques for AF MIMO relaying systems",   "publication": "Vehicular Technology Conference VTC -workshops",   "year": "2011" }, {  "paper_accepted": 1130,   "num_citations": 6,   "title": "Interference cancellation using relay station in heterogeneous networks",   "publication": "Vehicular Technology Conference VTC -workshops",   "year": "2011" }, {  "paper_accepted": 1130,   "num_citations": 6,   "title": "Necessity of phase ambiguity quantization for limited feedback coordinated multi-point transmission",   "publication": "Vehicular Technology Conference VTC -workshops",   "year": "2011" }, {  "paper_accepted": 1130,   "num_citations": 6,   "title": "Analytical design of inter-vehicular communications for collision avoidance",   "publication": "Vehicular Technology Conference VTC -workshops",   "year": "2011" }, {  "paper_accepted": 1130,   "num_citations": 7,   "title": "A non-cooperative game approach for bandwidth allocation in heterogeneous wireless networks",   "publication": "Vehicular Technology Conference VTC -workshops",   "year": "2011" }, {  "paper_accepted": 1130,   "num_citations": 6,   "title": "Analysis of utility-based data dissemination approaches in VANETs",   "publication": "Vehicular Technology Conference VTC -workshops",   "year": "2011" }, {  "paper_accepted": 1130,   "num_citations": 46,   "title": "Graph-based dynamic frequency reuse in femtocell networks",   "publication": "Vehicular Technology Conference VTC -workshops",   "year": "2011" }, {  "paper_accepted": 1130,   "num_citations": 5,   "title": "Dynamic spectrum sharing in femtocells: A comparison of selfish versus altruistic strategies",   "publication": "Vehicular Technology Conference VTC -workshops",   "year": "2011" }, {  "paper_accepted": 1130,   "num_citations": 5,   "title": "Dynamic sensor selection for target tracking in wireless sensor networks",   "publication": "Vehicular Technology Conference VTC -workshops",   "year": "2011" }, {  "paper_accepted": 1130,   "num_citations": 5,   "title": "Misbehavior Detection Without Channel Information in Cooperative Networks",   "publication": "Vehicular Technology Conference VTC -workshops",   "year": "2011" }, {  "paper_accepted": 1130,   "num_citations": 5,   "title": "CCH: Cognitive channel hopping in vehicular ad hoc networks",   "publication": "Vehicular Technology Conference VTC -workshops",   "year": "2011" }, {  "paper_accepted": 1130,   "num_citations": 6,   "title": "Adaptive harq with memoryless relays",   "publication": "Vehicular Technology Conference VTC -workshops",   "year": "2011" }, {  "paper_accepted": 1130,   "num_citations": 5,   "title": "Null Space Precoding for Downlink Network MIMO Systems with No CSI",   "publication": "Vehicular Technology Conference VTC -workshops",   "year": "2011" }, {  "paper_accepted": 1130,   "num_citations": 5,   "title": "Wireless power transmission for autonomous sensors in removable vehicle seats",   "publication": "Vehicular Technology Conference VTC -workshops",   "year": "2011" }, {  "paper_accepted": 1130,   "num_citations": 5,   "title": "Performance Evaluation of wiener filter designs for channel estimation in vehicular environments",   "publication": "Vehicular Technology Conference VTC -workshops",   "year": "2011" }, {  "paper_accepted": 1130,   "num_citations": 6,   "title": "Efficient channel estimation for single frequency broadcast systems",   "publication": "Vehicular Technology Conference VTC -workshops",   "year": "2011" }]}
