{"obj": [{  "paper_accepted": 945,   "num_citations": 5,   "title": "Hybrid cargo-level tracking system for logistics",   "publication": "Vehicular Technology Conference VTC -workshops",   "year": "2010" }, {  "paper_accepted": 945,   "num_citations": 5,   "title": "Performance evaluation of overhead reduction method for cyclostationarity-inducing transmission",   "publication": "Vehicular Technology Conference VTC -workshops",   "year": "2010" }, {  "paper_accepted": 945,   "num_citations": 5,   "title": "Coexistence of 802.11 b and 802.15. 4a-CSS: Measurements, Analytical Model and Simulation",   "publication": "Vehicular Technology Conference VTC -workshops",   "year": "2010" }, {  "paper_accepted": 945,   "num_citations": 5,   "title": "A Robust handover under analysis of unexpected vehicle behaviors in Vehicular Ad-hoc Network",   "publication": "Vehicular Technology Conference VTC -workshops",   "year": "2010" }, {  "paper_accepted": 945,   "num_citations": 5,   "title": "Channel-aware transmission control for cooperative random access networks",   "publication": "Vehicular Technology Conference VTC -workshops",   "year": "2010" }, {  "paper_accepted": 945,   "num_citations": 7,   "title": "Two-level HARQ for turbo coded cooperation",   "publication": "Vehicular Technology Conference VTC -workshops",   "year": "2010" }, {  "paper_accepted": 945,   "num_citations": 6,   "title": "Safe distance based location privacy in vehicular networks",   "publication": "Vehicular Technology Conference VTC -workshops",   "year": "2010" }, {  "paper_accepted": 945,   "num_citations": 6,   "title": "Handover scheme using uplink and downlink channel information in IEEE 802.16 e systems",   "publication": "Vehicular Technology Conference VTC -workshops",   "year": "2010" }, {  "paper_accepted": 945,   "num_citations": 5,   "title": "Distributed multiple access and flow control for wireless network coding",   "publication": "Vehicular Technology Conference VTC -workshops",   "year": "2010" }, {  "paper_accepted": 945,   "num_citations": 6,   "title": "Effect of imperfect channel estimation on multi-user beamforming in LTE-advanced system",   "publication": "Vehicular Technology Conference VTC -workshops",   "year": "2010" }, {  "paper_accepted": 945,   "num_citations": 6,   "title": "A Novel Inter-Cell Interference Coordination Scheme Based on Dynamic Resource Allocation in LTE-TDD Systems",   "publication": "Vehicular Technology Conference VTC -workshops",   "year": "2010" }, {  "paper_accepted": 945,   "num_citations": 5,   "title": "Cooperative correlation based spectrum sensing for dmb-t systems",   "publication": "Vehicular Technology Conference VTC -workshops",   "year": "2010" }, {  "paper_accepted": 945,   "num_citations": 29,   "title": "Energy efficiency of high QoS heterogeneous wireless communication network",   "publication": "Vehicular Technology Conference VTC -workshops",   "year": "2010" }, {  "paper_accepted": 945,   "num_citations": 30,   "title": "A simulation study of LTE intra-frequency handover performance",   "publication": "Vehicular Technology Conference VTC -workshops",   "year": "2010" }, {  "paper_accepted": 945,   "num_citations": 28,   "title": "Tou-aware energy management and wireless sensor networks for reducing peak load in smart grids",   "publication": "Vehicular Technology Conference VTC -workshops",   "year": "2010" }, {  "paper_accepted": 945,   "num_citations": 4,   "title": "Association Control Based Load Balancing for Tactical Information Communication Networks",   "publication": "Vehicular Technology Conference VTC -workshops",   "year": "2010" }, {  "paper_accepted": 945,   "num_citations": 7,   "title": "Directional Relay with Spatial Time Slot Scheduling for mmWave WPAN Systems",   "publication": "Vehicular Technology Conference VTC -workshops",   "year": "2010" }, {  "paper_accepted": 945,   "num_citations": 4,   "title": "A systematic LT coded arrangement for transmission over correlated shadow fading channels in 802.11 ad-hoc wireless networks",   "publication": "Vehicular Technology Conference VTC -workshops",   "year": "2010" }, {  "paper_accepted": 945,   "num_citations": 4,   "title": "Hybrid genetic algorithm for joint precoding and transmit antenna selection in multiuser MIMO systems with limited feedback",   "publication": "Vehicular Technology Conference VTC -workshops",   "year": "2010" }, {  "paper_accepted": 945,   "num_citations": 4,   "title": "A Demonstrator for Beamforming in C2X Communication",   "publication": "Vehicular Technology Conference VTC -workshops",   "year": "2010" }]}
