{"obj": [{  "paper_accepted": 470,   "num_citations": 1,   "title": "Using Multicast Transfers in the Replica Migration Problem: Formulation and Scheduling Heuristics",   "publication": "Euro-Par -Workshops -Symposium",   "year": "2009" }, {  "paper_accepted": 470,   "num_citations": 1,   "title": "A design pattern for component oriented development of agent based multithreaded applications",   "publication": "Euro-Par -Workshops -Symposium",   "year": "2008" }, {  "paper_accepted": 470,   "num_citations": 1,   "title": "Topic 7: Peer to Peer Computing",   "publication": "Euro-Par -Workshops -Symposium",   "year": "2012" }, {  "paper_accepted": 470,   "num_citations": 1,   "title": "Formal Model and Scheduling Heuristics for the Replica Migration Problem",   "publication": "Euro-Par -Workshops -Symposium",   "year": "2008" }, {  "paper_accepted": 470,   "num_citations": 1,   "title": "ASK: adaptive sampling kit for performance characterization",   "publication": "Euro-Par -Workshops -Symposium",   "year": "2012" }, {  "paper_accepted": 470,   "num_citations": 1,   "title": "Dependability analysis of a fault-tolerant network reconfiguring strategy",   "publication": "Euro-Par -Workshops -Symposium",   "year": "2009" }, {  "paper_accepted": 470,   "num_citations": 1,   "title": "Maximizing growth codes utility in large-scale wireless sensor networks",   "publication": "Euro-Par -Workshops -Symposium",   "year": "2010" }, {  "paper_accepted": 470,   "num_citations": 0,   "title": "Topic 1: Support Tools and Environments",   "publication": "Euro-Par -Workshops -Symposium",   "year": "2008" }, {  "paper_accepted": 470,   "num_citations": 0,   "title": "Ibis: A Programming System for Real-World Distributed Computing",   "publication": "Euro-Par -Workshops -Symposium",   "year": "2009" }, {  "paper_accepted": 470,   "num_citations": 0,   "title": "Topic 11: Multicore and Manycore Programming",   "publication": "Euro-Par -Workshops -Symposium",   "year": "2012" }, {  "paper_accepted": 470,   "num_citations": 0,   "title": "Analytical Evaluation of Clients&#39; Failures in a LVoD Architecture Based on P2P and Multicast Paradigms",   "publication": "Euro-Par -Workshops -Symposium",   "year": "2008" }, {  "paper_accepted": 470,   "num_citations": 0,   "title": "Object placement for cooperative caches with bandwidth constraints",   "publication": "Euro-Par -Workshops -Symposium",   "year": "2011" }, {  "paper_accepted": 470,   "num_citations": 0,   "title": "A fast parallel algorithm for minimum-cost small integral flows",   "publication": "Euro-Par -Workshops -Symposium",   "year": "2012" }, {  "paper_accepted": 470,   "num_citations": 0,   "title": "Mobile and ubiquitous computing",   "publication": "Euro-Par -Workshops -Symposium",   "year": "2010" }, {  "paper_accepted": 470,   "num_citations": 0,   "title": "Topic 10: Parallel Numerical Algorithms",   "publication": "Euro-Par -Workshops -Symposium",   "year": "2012" }, {  "paper_accepted": 470,   "num_citations": 0,   "title": "Progress guarantees when composing lock-free objects",   "publication": "Euro-Par -Workshops -Symposium",   "year": "2011" }, {  "paper_accepted": 470,   "num_citations": 0,   "title": "Topic 5: Parallel and Distributed Data Management",   "publication": "Euro-Par -Workshops -Symposium",   "year": "2012" }, {  "paper_accepted": 470,   "num_citations": 0,   "title": "CRAW/P: a workload partition method for the efficient parallel simulation of manycores",   "publication": "Euro-Par -Workshops -Symposium",   "year": "2012" }, {  "paper_accepted": 470,   "num_citations": 0,   "title": "HPC file systems in wide area networks: understanding the performance of lustre over WAN",   "publication": "Euro-Par -Workshops -Symposium",   "year": "2012" }, {  "paper_accepted": 470,   "num_citations": 0,   "title": "Theory and algorithms for parallel computation",   "publication": "Euro-Par -Workshops -Symposium",   "year": "2010" }]}
